thread6/__init__.py
thread6/tests.py
thread6/thread6.py
thread6-0.2.0.dist-info/METADATA
thread6-0.2.0.dist-info/RECORD
thread6-0.2.0.dist-info/WHEEL
thread6-0.2.0.dist-info/top_level.txt
