Metadata-Version: 2.1
Name: thread6
Version: 0.2.0
Summary: A plug n play multithreading interface
Home-page: https://github.com/Haizzz/thread6
Author: Anh Le
Author-email: hi@imanhle.com
License: UNKNOWN
Platform: UNKNOWN
Classifier: Programming Language :: Python :: 3
Classifier: License :: OSI Approved :: MIT License
Classifier: Operating System :: OS Independent
